<?xml version="1.0" encoding="UTF-8"?>
<objects serializationModel="Studio.02.02.00">
	<object class="ParameterPreset" id="{fb71242a-3174-43c1-b6db-e5810572e933}">
		<property name="name">
			<value>Continues</value>
		</property>
		<relationship name="folder">
			<destination>{1cafe93c-0422-40b2-8482-bfa682fbcdbe}</destination>
		</relationship>
		<relationship name="parameter">
			<destination>{84db9d34-eddc-43ff-a593-811f4fe4c769}</destination>
		</relationship>
	</object>
	<object class="GameParameter" id="{84db9d34-eddc-43ff-a593-811f4fe4c769}">
		<property name="maximum">
			<value>5</value>
		</property>
		<property name="initialValue">
			<value>5</value>
		</property>
	</object>
</objects>
